[
   {
      "file_info" : {
         "ALBUM" : "Drum 'N Bass Nation, Vol. 1",
         "ARTIST" : "Light Waves",
         "COMMENT" : "empty comment",
         "COMPOSER" : "",
         "DATE" : "10-03-2023",
         "DESCRIPTION" : "",
         "GENRE" : "Dance",
         "PERFORMER" : "",
         "TITLE" : "In The Space",
         "YEAR" : "0000"
      },
      "file_path" : "/home/varvara/Music/02 - Light Waves - In The Space.flac",
      "hash" : 0,
      "tags" : [ "33", "trhe", "ewrt" ]
   },
   {
      "file_info" : {
         "ALBUM" : "Drum 'N Bass Nation, Vol. 1",
         "ARTIST" : "Light Waves",
         "COMMENT" : "empty comment",
         "COMPOSER" : "",
         "DATE" : "10-03-2023",
         "DESCRIPTION" : "",
         "GENRE" : "Dance",
         "PERFORMER" : "",
         "TITLE" : "In The Space",
         "YEAR" : "0000"
      },
      "file_path" : "/home/varvara/Music/02 - Light Waves - In The Space.flac",
      "hash" : 0,
      "tags" : [ "33", "trhe", "ewrt" ]
   },
   {
      "file_info" : {
         "ALBUM" : "Drum 'N Bass Nation, Vol. 1",
         "ARTIST" : "Light Waves",
         "COMMENT" : "empty comment",
         "COMPOSER" : "",
         "DATE" : "10-03-2023",
         "DESCRIPTION" : "",
         "GENRE" : "Dance",
         "PERFORMER" : "",
         "TITLE" : "In The Space",
         "YEAR" : "0000"
      },
      "file_path" : "/home/varvara/Music/02 - Light Waves - In The Space.flac",
      "hash" : 0,
      "tags" : [ "33", "trhe", "ewrt" ]
   }
]
